outboxml/__init__.py
outboxml/analysis_tools.py
outboxml/automl_manager.py
outboxml/automl_utils.py
outboxml/config.py
outboxml/data_subsets.py
outboxml/datadrift.py
outboxml/dataset_retro.py
outboxml/datasets_manager.py
outboxml/ensemble.py
outboxml/export_results.py
outboxml/extractors.py
outboxml/feature_selection.py
outboxml/hyperparameter_tuning.py
outboxml/main_predict.py
outboxml/main_release.py
outboxml/models.py
outboxml/monitoring_manager.py
outboxml/monitoring_result.py
outboxml/plots.py
outboxml/service.py
outboxml/target_extrapolation.py
outboxml/__pycache__/__init__.cpython-313.pyc
outboxml/app/__init__.py
outboxml/app/fastapi/__init__.py
outboxml/app/fastapi/main.py
outboxml/app/fastapi/main_app.py
outboxml/core/__init__.py
outboxml/core/config_builders.py
outboxml/core/data_prepare.py
outboxml/core/email.py
outboxml/core/enums.py
outboxml/core/errors.py
outboxml/core/monitoring_factory.py
outboxml/core/pandas_prepare_engine.py
outboxml/core/predict.py
outboxml/core/prepared_datasets.py
outboxml/core/pydantic_models.py
outboxml/core/utils.py
outboxml/core/validators.py
outboxml/core/__pycache__/__init__.cpython-313.pyc
outboxml/core/__pycache__/pydantic_models.cpython-313.pyc
outboxml/dsml/__init__.py
outboxml/dsml/mailing.py
outboxml/metrics/__init__.py
outboxml/metrics/base_metrics.py
outboxml/metrics/business_metrics.py
outboxml/metrics/processor.py
outboxml-0.9.1.dist-info/licenses/LICENSE
outboxml-0.9.1.dist-info/METADATA
outboxml-0.9.1.dist-info/WHEEL
outboxml-0.9.1.dist-info/top_level.txt
outboxml-0.9.1.dist-info/RECORD
