Metadata-Version: 2.4
Name: outboxml
Version: 0.9.1
Summary: Framework for ML and DS
Author: VASuvorov
Author-email: justsuvorov@gmail.com
License: MIT
License-File: LICENSE
Requires-Dist: catboost==1.2.8
Requires-Dist: loguru==0.7.2
Requires-Dist: scikit-learn>=1.5.0
Requires-Dist: pydantic>=2.7.3
Requires-Dist: statsmodels>=0.14.2
Requires-Dist: pyarrow>=15.0.2
Requires-Dist: SQLAlchemy>=2.0.31
Requires-Dist: plotly==5.22.0
Requires-Dist: kaleido==0.2.1
Requires-Dist: mlflow>=2.16.0
Requires-Dist: pandas>=2.2.2
Requires-Dist: polars>1.33
Requires-Dist: numpy>=1.26.4
Requires-Dist: environs>=11.0.0
Requires-Dist: pretty_html_table==0.9.16
Requires-Dist: optbinning==0.20.0
Requires-Dist: ortools==9.14.6206
Requires-Dist: optuna>=4.1.0
Requires-Dist: openpyxl==3.1.5
Requires-Dist: nbformat==5.10.4
Requires-Dist: phik>=0.12.4
Requires-Dist: fastapi>=0.115.6
Requires-Dist: uvicorn>=0.34.0
Requires-Dist: schedule>=1.2.2
Requires-Dist: psycopg2-binary
Requires-Dist: scipy>=1.15.3
Requires-Dist: xgboost
Dynamic: author
Dynamic: author-email
Dynamic: license
Dynamic: license-file
Dynamic: requires-dist
Dynamic: summary
